ses_cloudwatch/__init__.py
ses_cloudwatch/py.typed
ses_cloudwatch/_jsii/__init__.py
ses_cloudwatch/_jsii/ses-cloudwatch@1.2.1.jsii.tgz
ses_cloudwatch-1.2.1.dist-info/LICENSE
ses_cloudwatch-1.2.1.dist-info/METADATA
ses_cloudwatch-1.2.1.dist-info/WHEEL
ses_cloudwatch-1.2.1.dist-info/top_level.txt
ses_cloudwatch-1.2.1.dist-info/RECORD
